flowkey_dl/__init__.py
flowkey_dl/flowkey_dl.py
flowkey_dl/flowkey_dl_cli.py
flowkey_dl/flowkey_dl_gui.py
flowkey_dl-0.1.10.dist-info/METADATA
flowkey_dl-0.1.10.dist-info/WHEEL
flowkey_dl-0.1.10.dist-info/entry_points.txt
flowkey_dl-0.1.10.dist-info/top_level.txt
flowkey_dl-0.1.10.dist-info/RECORD
