Metadata-Version: 2.1
Name: flowkey_dl
Version: 0.1.10
Summary: "A python app to download sheet music from flowkey and save it as pdf."
Home-page: https://github.com/MatthiasLienhard/flowkey_dl
Author: Matthias Lienhard
Author-email: mali27048@gmail.com
Project-URL: Bug Tracker, https://github.com/MatthiasLienhard/flowkey_dl/issues
Classifier: Programming Language :: Python :: 3
Classifier: License :: OSI Approved :: MIT License
Classifier: Operating System :: OS Independent
Requires-Python: >=3.6
Requires-Dist: requests
Requires-Dist: numpy
Requires-Dist: imageio
Requires-Dist: Pillow
Requires-Dist: matplotlib
Requires-Dist: importlib-metadata
